{
  "version": "7",
  "dialect": "sqlite",
  "entries": [
    {
      "idx": 0,
      "version": "6",
      "when": 1773523392712,
      "tag": "0000_dashing_fallen_one",
      "breakpoints": true
    },
    {
      "idx": 1,
      "version": "6",
      "when": 1775498423750,
      "tag": "0001_damp_psynapse",
      "breakpoints": true
    },
    {
      "idx": 2,
      "version": "6",
      "when": 1775510319873,
      "tag": "0002_fixed_killraven",
      "breakpoints": true
    },
    {
      "idx": 3,
      "version": "6",
      "when": 1775586051766,
      "tag": "0003_overconfident_loners",
      "breakpoints": true
    },
    {
      "idx": 4,
      "version": "6",
      "when": 1775795574894,
      "tag": "0004_cute_otto_octavius",
      "breakpoints": true
    },
    {
      "idx": 5,
      "version": "6",
      "when": 1776127748968,
      "tag": "0005_careless_charles_xavier",
      "breakpoints": true
    }
  ]
}